{
    "archives": {
        "overview:js_poster_circle": {
            "DEFAULT": "cros_ui_cases_000.wprgo"
        },
        "overview:multiwindow_five_real_pages:2019": {
            "DEFAULT": "cros_ui_cases_e1f4710580.wprgo"
        },
        "overview:multiwindow_ten_real_pages:2019": {
            "DEFAULT": "cros_ui_cases_e5c9fdfed0.wprgo"
        },
        "overview:yahoo_news": {
            "DEFAULT": "cros_ui_cases_000.wprgo"
        }
    },
    "description": "Describes the Web Page Replay archives for a story set. Don't edit by hand! Use record_wpr for updating.",
    "platform_specific": true
}
