{
  "$build/chromium_tests_builder_config": {
    "builder_config": {
      "builder_db": {
        "entries": [
          {
            "builder_id": {
              "bucket": "goma",
              "builder": "Chromium Mac Goma RBE Staging (dbg)",
              "project": "chromium"
            },
            "builder_spec": {
              "builder_group": "chromium.goma",
              "execution_mode": "COMPILE_AND_TEST",
              "legacy_chromium_config": {
                "apply_configs": [
                  "mb",
                  "goma_failfast"
                ],
                "config": "chromium",
                "target_bits": 64
              },
              "legacy_gclient_config": {
                "config": "chromium"
              }
            }
          }
        ]
      },
      "builder_ids": [
        {
          "bucket": "goma",
          "builder": "Chromium Mac Goma RBE Staging (dbg)",
          "project": "chromium"
        }
      ]
    }
  },
  "$build/goma": {
    "jobs": 80,
    "rpc_extra_params": "?staging",
    "server_host": "staging-goma.chromium.org"
  },
  "$recipe_engine/resultdb/test_presentation": {
    "column_keys": [],
    "grouping_keys": [
      "status",
      "v.test_suite"
    ]
  },
  "builder_group": "chromium.goma",
  "recipe": "chromium"
}