{
    "bullseye_amd64": {
        "Sha256Sum": "68d9889fc4926ac42e49cb9871e481de712bfa9a90f4fbb0a398dbff82c3d831",
        "SysrootDir": "debian_bullseye_amd64-sysroot",
        "Tarball": "debian_bullseye_amd64_sysroot.tar.xz",
        "URL": "https://commondatastorage.googleapis.com/chrome-linux-sysroot"
    },
    "bullseye_arm64": {
        "Sha256Sum": "f78b961f42716c754c8fbaafd047538860d4cfe91e179f4da06c9e0874ede24c",
        "SysrootDir": "debian_bullseye_arm64-sysroot",
        "Tarball": "debian_bullseye_arm64_sysroot.tar.xz",
        "URL": "https://commondatastorage.googleapis.com/chrome-linux-sysroot"
    },
    "bullseye_armhf": {
        "Sha256Sum": "809cb5d0205a983027c60e4e292ea0d4db09193461605fcb2c69f21752d7ba8f",
        "SysrootDir": "debian_bullseye_armhf-sysroot",
        "Tarball": "debian_bullseye_armhf_sysroot.tar.xz",
        "URL": "https://commondatastorage.googleapis.com/chrome-linux-sysroot"
    },
    "bullseye_i386": {
        "Sha256Sum": "01c02e3bc05dd2c92587d521d4fc8865dff4c7558578032d775bdb9384ffaa2f",
        "SysrootDir": "debian_bullseye_i386-sysroot",
        "Tarball": "debian_bullseye_i386_sysroot.tar.xz",
        "URL": "https://commondatastorage.googleapis.com/chrome-linux-sysroot"
    },
    "bullseye_mips64el": {
        "Sha256Sum": "fc6654e7e9e74213e3c242d5ec6da28d3cb3f6eb66d6aee4a4b624407827846b",
        "SysrootDir": "debian_bullseye_mips64el-sysroot",
        "Tarball": "debian_bullseye_mips64el_sysroot.tar.xz",
        "URL": "https://commondatastorage.googleapis.com/chrome-linux-sysroot"
    },
    "bullseye_mipsel": {
        "Sha256Sum": "9681b26951bd8a49befa52f50d789920d4f0c312f23971dcd7ae67ac463ebfbe",
        "SysrootDir": "debian_bullseye_mipsel-sysroot",
        "Tarball": "debian_bullseye_mipsel_sysroot.tar.xz",
        "URL": "https://commondatastorage.googleapis.com/chrome-linux-sysroot"
    }
}
