{
  "gn_args": {
    "android_static_analysis": "off",
    "dcheck_always_on": true,
    "debuggable_apks": false,
    "ffmpeg_branding": "Chrome",
    "is_component_build": false,
    "is_debug": false,
    "proprietary_codecs": true,
    "strip_debug_info": true,
    "symbol_level": 0,
    "system_webview_package_name": "com.google.android.apps.chrome",
    "system_webview_shell_package_name": "org.chromium.my_webview_shell",
    "target_cpu": "x86",
    "target_os": "android",
    "use_remoteexec": true,
    "use_siso": true
  }
}