{"layers":[{"nm":"Gradient","ddd":0,"ty":0,"ind":1,"sr":1,"ip":0,"op":310,"st":0,"ks":{"a":{"k":[921,158,0],"ix":1,"a":0},"p":{"ix":2,"a":1,"k":[{"t":84,"i":{"x":[0.833],"y":[0.833]},"o":{"x":[0.167],"y":[0.167]},"s":[-305,84,0]},{"t":179,"s":[921.022,84,0]}]},"s":{"k":[100,100,100],"ix":6,"a":0},"r":{"k":0,"ix":10,"a":0},"o":{"k":100,"ix":11,"a":0}},"ao":0,"bm":0,"td":1,"refId":"comp_0","w":1842,"h":316},{"nm":"lines 2","ddd":0,"ty":0,"ind":2,"sr":1,"ip":-73,"op":527,"st":-73,"ks":{"a":{"k":[307,84,0],"ix":1,"a":0},"p":{"k":[307,84,0],"ix":2,"a":0},"s":{"k":[100,100,100],"ix":6,"a":0},"r":{"k":0,"ix":10,"a":0},"o":{"k":100,"ix":11,"a":0}},"ao":0,"bm":0,"tt":3,"refId":"comp_1","w":614,"h":168},{"nm":"lines","ddd":0,"ty":0,"ind":3,"sr":1,"ip":-73,"op":527,"st":-73,"ks":{"a":{"k":[307,84,0],"ix":1,"a":0},"p":{"k":[307,84,0],"ix":2,"a":0},"s":{"k":[100,100,100],"ix":6,"a":0},"r":{"k":0,"ix":10,"a":0},"o":{"k":100,"ix":11,"a":0}},"ao":0,"bm":0,"refId":"comp_2","w":614,"h":168}],"nm":"mahi_line_gradient","v":"5.9.3","fr":60,"ip":0,"op":180,"w":614,"h":168,"ddd":0,"assets":[{"nm":"Pre-comp 1","id":"comp_0","layers":[{"nm":"Shape Layer 5","ddd":0,"ty":4,"ind":1,"parent":3,"sr":1,"ip":0,"op":377,"st":0,"ks":{"a":{"k":[0,0,0],"ix":1,"a":0},"p":{"k":[-1227,0,0],"ix":2,"a":0},"s":{"k":[100,100,100],"ix":6,"a":0},"r":{"k":0,"ix":10,"a":0},"o":{"k":100,"ix":11,"a":0}},"ao":0,"bm":0,"ef":[{"nm":"Gradient Ramp","mn":"ADBE Ramp","ix":1,"ty":5,"ef":[{"nm":"Start of Ramp","mn":"ADBE Ramp-0001","ix":1,"ty":3,"v":{"k":[78,214],"ix":1,"a":0}},{"nm":"Start Color","mn":"ADBE Ramp-0002","ix":2,"ty":2,"v":{"k":[1,1,1,1],"ix":2,"a":0}},{"nm":"End of Ramp","mn":"ADBE Ramp-0003","ix":3,"ty":3,"v":{"k":[576,314],"ix":3,"a":0}},{"nm":"cros.sys.illo.base","mn":"ADBE Ramp-0004","ix":4,"ty":2,"v":{"k":[1,1,1,1],"ix":4,"a":0}},{"nm":"Ramp Shape","mn":"ADBE Ramp-0005","ix":5,"ty":7,"v":{"k":1,"ix":5,"a":0}},{"nm":"Ramp Scatter","mn":"ADBE Ramp-0006","ix":6,"ty":0,"v":{"k":0,"ix":6,"a":0}},{"nm":"Blend With Original","mn":"ADBE Ramp-0007","ix":7,"ty":0,"v":{"k":0,"ix":7,"a":0}},{"nm":"","mn":"ADBE Ramp-0008","ix":8,"ty":6,"v":0}],"en":true}],"shapes":[{"nm":"Rectangle 1","mn":"ADBE Vector Group","hd":false,"ty":"gr","bm":0,"ix":1,"np":3,"it":[{"nm":"Rectangle Path 1","mn":"ADBE Vector Shape - Rect","hd":false,"ty":"rc","d":1,"p":{"k":[0,0],"ix":3,"a":0},"s":{"k":[615.586,170.129],"ix":2,"a":0},"r":{"k":0,"ix":4,"a":0}},{"nm":"cros.sys.illo.base","mn":"ADBE Vector Graphic - Stroke","hd":false,"ty":"st","bm":0,"lc":1,"lj":1,"ml":4,"o":{"k":100,"ix":4,"a":0},"w":{"k":0,"ix":5,"a":0},"c":{"k":[1,1,1,1],"ix":3,"a":0}},{"nm":"cros.sys.base-elevated","mn":"ADBE Vector Graphic - Fill","hd":false,"ty":"fl","bm":0,"o":{"k":100,"ix":5,"a":0},"c":{"k":[1,1,1,1],"ix":4,"a":0},"r":1},{"nm":"Transform","ty":"tr","a":{"k":[0,0],"ix":1,"a":0},"p":{"k":[-1.207,-1.936],"ix":2,"a":0},"s":{"k":[100,100],"ix":3,"a":0},"r":{"k":0,"ix":6,"a":0},"o":{"k":100,"ix":7,"a":0},"sk":{"k":0,"ix":4,"a":0},"sa":{"k":0,"ix":5,"a":0}}]}]},{"nm":"Shape Layer 3","ddd":0,"ty":4,"ind":2,"parent":3,"sr":1,"ip":0,"op":405,"st":0,"ks":{"a":{"k":[0,0,0],"ix":1,"a":0},"p":{"k":[-613,0,0],"ix":2,"a":0},"s":{"k":[100,100,100],"ix":6,"a":0},"r":{"k":0,"ix":10,"a":0},"o":{"k":100,"ix":11,"a":0}},"ao":0,"bm":0,"ef":[{"nm":"Gradient Ramp","mn":"ADBE Ramp","ix":1,"ty":5,"ef":[{"nm":"Start of Ramp","mn":"ADBE Ramp-0001","ix":1,"ty":3,"v":{"k":[1093,227],"ix":1,"a":0}},{"nm":"Start Color","mn":"ADBE Ramp-0002","ix":2,"ty":2,"v":{"k":[1,1,1,1],"ix":2,"a":0}},{"nm":"End of Ramp","mn":"ADBE Ramp-0003","ix":3,"ty":3,"v":{"k":[680,78],"ix":3,"a":0}},{"nm":"cros.sys.illo.base","mn":"ADBE Ramp-0004","ix":4,"ty":2,"v":{"k":[1,1,1,1],"ix":4,"a":0}},{"nm":"Ramp Shape","mn":"ADBE Ramp-0005","ix":5,"ty":7,"v":{"k":1,"ix":5,"a":0}},{"nm":"Ramp Scatter","mn":"ADBE Ramp-0006","ix":6,"ty":0,"v":{"k":0,"ix":6,"a":0}},{"nm":"Blend With Original","mn":"ADBE Ramp-0007","ix":7,"ty":0,"v":{"k":0,"ix":7,"a":0}},{"nm":"","mn":"ADBE Ramp-0008","ix":8,"ty":6,"v":0}],"en":true}],"shapes":[{"nm":"Rectangle 1","mn":"ADBE Vector Group","hd":false,"ty":"gr","bm":0,"ix":1,"np":3,"it":[{"nm":"Rectangle Path 1","mn":"ADBE Vector Shape - Rect","hd":false,"ty":"rc","d":1,"p":{"k":[0,0],"ix":3,"a":0},"s":{"k":[615.586,170.129],"ix":2,"a":0},"r":{"k":0,"ix":4,"a":0}},{"nm":"cros.sys.illo.base","mn":"ADBE Vector Graphic - Stroke","hd":false,"ty":"st","bm":0,"lc":1,"lj":1,"ml":4,"o":{"k":100,"ix":4,"a":0},"w":{"k":0,"ix":5,"a":0},"c":{"k":[1,1,1,1],"ix":3,"a":0}},{"nm":"cros.sys.base-elevated","mn":"ADBE Vector Graphic - Fill","hd":false,"ty":"fl","bm":0,"o":{"k":100,"ix":5,"a":0},"c":{"k":[1,1,1,1],"ix":4,"a":0},"r":1},{"nm":"Transform","ty":"tr","a":{"k":[0,0],"ix":1,"a":0},"p":{"k":[-1.207,-1.936],"ix":2,"a":0},"s":{"k":[100,100],"ix":3,"a":0},"r":{"k":0,"ix":6,"a":0},"o":{"k":100,"ix":7,"a":0},"sk":{"k":0,"ix":4,"a":0},"sa":{"k":0,"ix":5,"a":0}}]}]},{"nm":"Shape Layer 4","ddd":0,"ty":4,"ind":3,"sr":1,"ip":-37,"op":339,"st":33,"ks":{"a":{"k":[0,0,0],"ix":1,"a":0},"p":{"k":[1535.2,172,0],"ix":2,"a":0},"s":{"k":[100,214.943,100],"ix":6,"a":0},"r":{"k":0,"ix":10,"a":0},"o":{"k":100,"ix":11,"a":0}},"ao":0,"bm":0,"ef":[{"nm":"Gradient Ramp","mn":"ADBE Ramp","ix":1,"ty":5,"ef":[{"nm":"Start of Ramp","mn":"ADBE Ramp-0001","ix":1,"ty":3,"v":{"k":[1774,314],"ix":1,"a":0}},{"nm":"cros.sys.illo.base","mn":"ADBE Ramp-0002","ix":2,"ty":2,"v":{"k":[1,1,1,1],"ix":2,"a":0}},{"nm":"End of Ramp","mn":"ADBE Ramp-0003","ix":3,"ty":3,"v":{"k":[1317,216],"ix":3,"a":0}},{"nm":"End Color","mn":"ADBE Ramp-0004","ix":4,"ty":2,"v":{"k":[1,1,1,1],"ix":4,"a":0}},{"nm":"Ramp Shape","mn":"ADBE Ramp-0005","ix":5,"ty":7,"v":{"k":1,"ix":5,"a":0}},{"nm":"Ramp Scatter","mn":"ADBE Ramp-0006","ix":6,"ty":0,"v":{"k":0,"ix":6,"a":0}},{"nm":"Blend With Original","mn":"ADBE Ramp-0007","ix":7,"ty":0,"v":{"k":0,"ix":7,"a":0}},{"nm":"","mn":"ADBE Ramp-0008","ix":8,"ty":6,"v":0}],"en":true}],"shapes":[{"nm":"Rectangle 1","mn":"ADBE Vector Group","hd":false,"ty":"gr","bm":0,"ix":1,"np":3,"it":[{"nm":"Rectangle Path 1","mn":"ADBE Vector Shape - Rect","hd":false,"ty":"rc","d":1,"p":{"k":[0,0],"ix":3,"a":0},"s":{"k":[615.586,170.129],"ix":2,"a":0},"r":{"k":0,"ix":4,"a":0}},{"nm":"cros.sys.illo.base","mn":"ADBE Vector Graphic - Stroke","hd":false,"ty":"st","bm":0,"lc":1,"lj":1,"ml":4,"o":{"k":100,"ix":4,"a":0},"w":{"k":0,"ix":5,"a":0},"c":{"k":[1,1,1,1],"ix":3,"a":0}},{"nm":"cros.sys.base-elevated","mn":"ADBE Vector Graphic - Fill","hd":false,"ty":"fl","bm":0,"o":{"k":100,"ix":5,"a":0},"c":{"k":[1,1,1,1],"ix":4,"a":0},"r":1},{"nm":"Transform","ty":"tr","a":{"k":[0,0],"ix":1,"a":0},"p":{"k":[-1.207,-1.936],"ix":2,"a":0},"s":{"k":[100,100],"ix":3,"a":0},"r":{"k":0,"ix":6,"a":0},"o":{"k":100,"ix":7,"a":0},"sk":{"k":0,"ix":4,"a":0},"sa":{"k":0,"ix":5,"a":0}}]}]}],"fr":60},{"nm":"lines 2","id":"comp_1","layers":[{"nm":"1","ddd":0,"ty":4,"ind":1,"sr":1,"ip":0,"op":757,"st":0,"ks":{"a":{"k":[0,0,0],"ix":1,"a":0},"p":{"k":[-413,-400,0],"ix":2,"a":0},"s":{"k":[100,100,100],"ix":6,"a":0},"r":{"k":0,"ix":10,"a":0},"o":{"k":100,"ix":11,"a":0}},"ao":0,"bm":0,"shapes":[{"nm":"Shape 1","mn":"ADBE Vector Group","hd":false,"ty":"gr","bm":0,"ix":1,"np":3,"it":[{"nm":"Path 1","mn":"ADBE Vector Shape - Group","hd":false,"ty":"sh","ix":1,"ks":{"k":{"c":false,"i":[[-546,0],[0.927,0],[0,0]],"o":[[220.67,0],[-1.367,0],[0,0]],"v":[[418,424],[719.14,424],[556.758,424]]},"ix":2,"a":0},"ind":0},{"nm":"cros.sys.illo.complement","mn":"ADBE Vector Graphic - Stroke","hd":false,"ty":"st","bm":0,"lc":2,"lj":2,"o":{"k":100,"ix":4,"a":0},"w":{"k":31,"ix":5,"a":0},"c":{"k":[0.7019607843137254,0.9372549019607843,0.8313725490196079,1],"ix":3,"a":0}},{"nm":"Transform","ty":"tr","a":{"k":[0,0],"ix":1,"a":0},"p":{"k":[0,0],"ix":2,"a":0},"s":{"k":[103.457,99.837],"ix":3,"a":0},"r":{"k":0,"ix":6,"a":0},"o":{"k":100,"ix":7,"a":0},"sk":{"k":0,"ix":4,"a":0},"sa":{"k":0,"ix":5,"a":0}}]},{"nm":"Trim Paths 1","mn":"ADBE Vector Filter - Trim","hd":false,"ty":"tm","ix":2,"s":{"k":0,"ix":1,"a":0},"e":{"k":[{"t":73,"i":{"x":[0],"y":[1]},"o":{"x":[0.2],"y":[0]},"s":[0]},{"t":140,"s":[100]}],"ix":2,"a":1},"o":{"k":0,"ix":3,"a":0},"m":1}]},{"nm":"2","ddd":0,"ty":4,"ind":2,"sr":1,"ip":0,"op":757,"st":0,"ks":{"a":{"k":[0,0,0],"ix":1,"a":0},"p":{"k":[-421,-359,0],"ix":2,"a":0},"s":{"k":[100,100,100],"ix":6,"a":0},"r":{"k":0,"ix":10,"a":0},"o":{"k":100,"ix":11,"a":0}},"ao":0,"bm":0,"shapes":[{"nm":"Shape 1","mn":"ADBE Vector Group","hd":false,"ty":"gr","bm":0,"ix":1,"np":3,"it":[{"nm":"Path 1","mn":"ADBE Vector Shape - Group","hd":false,"ty":"sh","ix":1,"ks":{"k":{"c":false,"i":[[0,0],[0,0]],"o":[[0,0],[0,0]],"v":[[424.766,424],[981.089,424]]},"ix":2,"a":0},"ind":0},{"nm":"cros.sys.illo.complement","mn":"ADBE Vector Graphic - Stroke","hd":false,"ty":"st","bm":0,"lc":2,"lj":1,"ml":4,"o":{"k":100,"ix":4,"a":0},"w":{"k":31,"ix":5,"a":0},"c":{"k":[0.7019607843137254,0.9372549019607843,0.8313725490196079,1],"ix":3,"a":0}},{"nm":"Transform","ty":"tr","a":{"k":[0,0],"ix":1,"a":0},"p":{"k":[0,0],"ix":2,"a":0},"s":{"k":[103.457,99.837],"ix":3,"a":0},"r":{"k":0,"ix":6,"a":0},"o":{"k":100,"ix":7,"a":0},"sk":{"k":0,"ix":4,"a":0},"sa":{"k":0,"ix":5,"a":0}}]},{"nm":"Trim Paths 1","mn":"ADBE Vector Filter - Trim","hd":false,"ty":"tm","ix":2,"s":{"k":0,"ix":1,"a":0},"e":{"k":[{"t":88,"i":{"x":[0],"y":[1]},"o":{"x":[0.2],"y":[0]},"s":[0]},{"t":128,"s":[100]}],"ix":2,"a":1},"o":{"k":0,"ix":3,"a":0},"m":1}]},{"nm":"5","ddd":0,"ty":4,"ind":3,"sr":1,"ip":0,"op":757,"st":0,"ks":{"a":{"k":[0,0,0],"ix":1,"a":0},"p":{"k":[-421,-320,0],"ix":2,"a":0},"s":{"k":[100,100,100],"ix":6,"a":0},"r":{"k":0,"ix":10,"a":0},"o":{"k":100,"ix":11,"a":0}},"ao":0,"bm":0,"shapes":[{"nm":"Shape 1","mn":"ADBE Vector Group","hd":false,"ty":"gr","bm":0,"ix":1,"np":3,"it":[{"nm":"Path 1","mn":"ADBE Vector Shape - Group","hd":false,"ty":"sh","ix":1,"ks":{"k":{"c":false,"i":[[0,0],[0,0]],"o":[[0,0],[0,0]],"v":[[424.766,424],[981.089,424]]},"ix":2,"a":0},"ind":0},{"nm":"cros.sys.illo.complement","mn":"ADBE Vector Graphic - Stroke","hd":false,"ty":"st","bm":0,"lc":2,"lj":1,"ml":4,"o":{"k":100,"ix":4,"a":0},"w":{"k":31,"ix":5,"a":0},"c":{"k":[0.7019607843137254,0.9372549019607843,0.8313725490196079,1],"ix":3,"a":0}},{"nm":"Transform","ty":"tr","a":{"k":[0,0],"ix":1,"a":0},"p":{"k":[0,0],"ix":2,"a":0},"s":{"k":[103.457,99.837],"ix":3,"a":0},"r":{"k":0,"ix":6,"a":0},"o":{"k":100,"ix":7,"a":0},"sk":{"k":0,"ix":4,"a":0},"sa":{"k":0,"ix":5,"a":0}}]},{"nm":"Trim Paths 1","mn":"ADBE Vector Filter - Trim","hd":false,"ty":"tm","ix":2,"s":{"k":0,"ix":1,"a":0},"e":{"k":[{"t":104,"i":{"x":[0],"y":[1]},"o":{"x":[0.2],"y":[0]},"s":[0]},{"t":144,"s":[100]}],"ix":2,"a":1},"o":{"k":0,"ix":3,"a":0},"m":1}]},{"nm":"6","ddd":0,"ty":4,"ind":4,"sr":1,"ip":0,"op":757,"st":0,"ks":{"a":{"k":[0,0,0],"ix":1,"a":0},"p":{"k":[-421,-280,0],"ix":2,"a":0},"s":{"k":[100,100,100],"ix":6,"a":0},"r":{"k":0,"ix":10,"a":0},"o":{"k":100,"ix":11,"a":0}},"ao":0,"bm":0,"shapes":[{"nm":"Shape 1","mn":"ADBE Vector Group","hd":false,"ty":"gr","bm":0,"ix":1,"np":3,"it":[{"nm":"Path 1","mn":"ADBE Vector Shape - Group","hd":false,"ty":"sh","ix":1,"ks":{"k":{"c":false,"i":[[0,0],[0,0]],"o":[[0,0],[0,0]],"v":[[424.766,424],[981.089,424]]},"ix":2,"a":0},"ind":0},{"nm":"cros.sys.illo.complement","mn":"ADBE Vector Graphic - Stroke","hd":false,"ty":"st","bm":0,"lc":2,"lj":1,"ml":4,"o":{"k":100,"ix":4,"a":0},"w":{"k":31,"ix":5,"a":0},"c":{"k":[0.7019607843137254,0.9372549019607843,0.8313725490196079,1],"ix":3,"a":0}},{"nm":"Transform","ty":"tr","a":{"k":[0,0],"ix":1,"a":0},"p":{"k":[0,0],"ix":2,"a":0},"s":{"k":[103.457,99.837],"ix":3,"a":0},"r":{"k":0,"ix":6,"a":0},"o":{"k":100,"ix":7,"a":0},"sk":{"k":0,"ix":4,"a":0},"sa":{"k":0,"ix":5,"a":0}}]},{"nm":"Trim Paths 1","mn":"ADBE Vector Filter - Trim","hd":false,"ty":"tm","ix":2,"s":{"k":0,"ix":1,"a":0},"e":{"k":[{"t":116,"i":{"x":[0],"y":[1]},"o":{"x":[0.2],"y":[0]},"s":[0]},{"t":156,"s":[100]}],"ix":2,"a":1},"o":{"k":0,"ix":3,"a":0},"m":1}]}],"fr":60},{"nm":"lines","id":"comp_2","layers":[{"nm":"1","ddd":0,"ty":4,"ind":1,"sr":1,"ip":0,"op":757,"st":0,"ks":{"a":{"k":[0,0,0],"ix":1,"a":0},"p":{"k":[-413,-400,0],"ix":2,"a":0},"s":{"k":[100,100,100],"ix":6,"a":0},"r":{"k":0,"ix":10,"a":0},"o":{"k":100,"ix":11,"a":0}},"ao":0,"bm":0,"shapes":[{"nm":"Shape 1","mn":"ADBE Vector Group","hd":false,"ty":"gr","bm":0,"ix":1,"np":3,"it":[{"nm":"Path 1","mn":"ADBE Vector Shape - Group","hd":false,"ty":"sh","ix":1,"ks":{"k":{"c":false,"i":[[-546,0],[0.927,0],[0,0]],"o":[[220.67,0],[-1.367,0],[0,0]],"v":[[418,424],[719.14,424],[556.758,424]]},"ix":2,"a":0},"ind":0},{"nm":"cros.sys.illo.analog","mn":"ADBE Vector Graphic - Stroke","hd":false,"ty":"st","bm":0,"lc":2,"lj":2,"o":{"k":100,"ix":4,"a":0},"w":{"k":31,"ix":5,"a":0},"c":{"k":[0.615686274509804,0.6392156862745098,1,1],"ix":3,"a":0}},{"nm":"Transform","ty":"tr","a":{"k":[0,0],"ix":1,"a":0},"p":{"k":[0,0],"ix":2,"a":0},"s":{"k":[103.457,99.837],"ix":3,"a":0},"r":{"k":0,"ix":6,"a":0},"o":{"k":100,"ix":7,"a":0},"sk":{"k":0,"ix":4,"a":0},"sa":{"k":0,"ix":5,"a":0}}]},{"nm":"Trim Paths 1","mn":"ADBE Vector Filter - Trim","hd":false,"ty":"tm","ix":2,"s":{"k":0,"ix":1,"a":0},"e":{"k":[{"t":73,"i":{"x":[0],"y":[1]},"o":{"x":[0.2],"y":[0]},"s":[0]},{"t":140,"s":[100]}],"ix":2,"a":1},"o":{"k":0,"ix":3,"a":0},"m":1}]},{"nm":"2","ddd":0,"ty":4,"ind":2,"sr":1,"ip":0,"op":757,"st":0,"ks":{"a":{"k":[0,0,0],"ix":1,"a":0},"p":{"k":[-421,-359,0],"ix":2,"a":0},"s":{"k":[100,100,100],"ix":6,"a":0},"r":{"k":0,"ix":10,"a":0},"o":{"k":100,"ix":11,"a":0}},"ao":0,"bm":0,"shapes":[{"nm":"Shape 1","mn":"ADBE Vector Group","hd":false,"ty":"gr","bm":0,"ix":1,"np":3,"it":[{"nm":"Path 1","mn":"ADBE Vector Shape - Group","hd":false,"ty":"sh","ix":1,"ks":{"k":{"c":false,"i":[[0,0],[0,0]],"o":[[0,0],[0,0]],"v":[[424.766,424],[981.089,424]]},"ix":2,"a":0},"ind":0},{"nm":"cros.sys.illo.analog","mn":"ADBE Vector Graphic - Stroke","hd":false,"ty":"st","bm":0,"lc":2,"lj":1,"ml":4,"o":{"k":100,"ix":4,"a":0},"w":{"k":31,"ix":5,"a":0},"c":{"k":[0.615686274509804,0.6392156862745098,1,1],"ix":3,"a":0}},{"nm":"Transform","ty":"tr","a":{"k":[0,0],"ix":1,"a":0},"p":{"k":[0,0],"ix":2,"a":0},"s":{"k":[103.457,99.837],"ix":3,"a":0},"r":{"k":0,"ix":6,"a":0},"o":{"k":100,"ix":7,"a":0},"sk":{"k":0,"ix":4,"a":0},"sa":{"k":0,"ix":5,"a":0}}]},{"nm":"Trim Paths 1","mn":"ADBE Vector Filter - Trim","hd":false,"ty":"tm","ix":2,"s":{"k":0,"ix":1,"a":0},"e":{"k":[{"t":88,"i":{"x":[0],"y":[1]},"o":{"x":[0.2],"y":[0]},"s":[0]},{"t":128,"s":[100]}],"ix":2,"a":1},"o":{"k":0,"ix":3,"a":0},"m":1}]},{"nm":"5","ddd":0,"ty":4,"ind":3,"sr":1,"ip":0,"op":757,"st":0,"ks":{"a":{"k":[0,0,0],"ix":1,"a":0},"p":{"k":[-421,-320,0],"ix":2,"a":0},"s":{"k":[100,100,100],"ix":6,"a":0},"r":{"k":0,"ix":10,"a":0},"o":{"k":100,"ix":11,"a":0}},"ao":0,"bm":0,"shapes":[{"nm":"Shape 1","mn":"ADBE Vector Group","hd":false,"ty":"gr","bm":0,"ix":1,"np":3,"it":[{"nm":"Path 1","mn":"ADBE Vector Shape - Group","hd":false,"ty":"sh","ix":1,"ks":{"k":{"c":false,"i":[[0,0],[0,0]],"o":[[0,0],[0,0]],"v":[[424.766,424],[981.089,424]]},"ix":2,"a":0},"ind":0},{"nm":"cros.sys.illo.analog","mn":"ADBE Vector Graphic - Stroke","hd":false,"ty":"st","bm":0,"lc":2,"lj":1,"ml":4,"o":{"k":100,"ix":4,"a":0},"w":{"k":31,"ix":5,"a":0},"c":{"k":[0.615686274509804,0.6392156862745098,1,1],"ix":3,"a":0}},{"nm":"Transform","ty":"tr","a":{"k":[0,0],"ix":1,"a":0},"p":{"k":[0,0],"ix":2,"a":0},"s":{"k":[103.457,99.837],"ix":3,"a":0},"r":{"k":0,"ix":6,"a":0},"o":{"k":100,"ix":7,"a":0},"sk":{"k":0,"ix":4,"a":0},"sa":{"k":0,"ix":5,"a":0}}]},{"nm":"Trim Paths 1","mn":"ADBE Vector Filter - Trim","hd":false,"ty":"tm","ix":2,"s":{"k":0,"ix":1,"a":0},"e":{"k":[{"t":104,"i":{"x":[0],"y":[1]},"o":{"x":[0.2],"y":[0]},"s":[0]},{"t":144,"s":[100]}],"ix":2,"a":1},"o":{"k":0,"ix":3,"a":0},"m":1}]},{"nm":"6","ddd":0,"ty":4,"ind":4,"sr":1,"ip":0,"op":757,"st":0,"ks":{"a":{"k":[0,0,0],"ix":1,"a":0},"p":{"k":[-421,-280,0],"ix":2,"a":0},"s":{"k":[100,100,100],"ix":6,"a":0},"r":{"k":0,"ix":10,"a":0},"o":{"k":100,"ix":11,"a":0}},"ao":0,"bm":0,"shapes":[{"nm":"Shape 1","mn":"ADBE Vector Group","hd":false,"ty":"gr","bm":0,"ix":1,"np":3,"it":[{"nm":"Path 1","mn":"ADBE Vector Shape - Group","hd":false,"ty":"sh","ix":1,"ks":{"k":{"c":false,"i":[[0,0],[0,0]],"o":[[0,0],[0,0]],"v":[[424.766,424],[981.089,424]]},"ix":2,"a":0},"ind":0},{"nm":"cros.sys.illo.analog","mn":"ADBE Vector Graphic - Stroke","hd":false,"ty":"st","bm":0,"lc":2,"lj":1,"ml":4,"o":{"k":100,"ix":4,"a":0},"w":{"k":31,"ix":5,"a":0},"c":{"k":[0.615686274509804,0.6392156862745098,1,1],"ix":3,"a":0}},{"nm":"Transform","ty":"tr","a":{"k":[0,0],"ix":1,"a":0},"p":{"k":[0,0],"ix":2,"a":0},"s":{"k":[103.457,99.837],"ix":3,"a":0},"r":{"k":0,"ix":6,"a":0},"o":{"k":100,"ix":7,"a":0},"sk":{"k":0,"ix":4,"a":0},"sa":{"k":0,"ix":5,"a":0}}]},{"nm":"Trim Paths 1","mn":"ADBE Vector Filter - Trim","hd":false,"ty":"tm","ix":2,"s":{"k":0,"ix":1,"a":0},"e":{"k":[{"t":116,"i":{"x":[0],"y":[1]},"o":{"x":[0.2],"y":[0]},"s":[0]},{"t":156,"s":[100]}],"ix":2,"a":1},"o":{"k":0,"ix":3,"a":0},"m":1}]}],"fr":60}],"markers":[{"cm":"_CrOS_Marker_CycleRestart_Line","tm":84,"dr":0}]}