{"layers":[{"nm":"Gradient","ddd":0,"ty":0,"ind":1,"sr":1,"ip":0,"op":310,"st":0,"ks":{"a":{"k":[921,158,0],"ix":1,"a":0},"p":{"ix":2,"a":1,"k":[{"t":40,"i":{"x":[0.833],"y":[0.833]},"o":{"x":[0.167],"y":[0.167]},"s":[-305,154,0]},{"t":135,"s":[921.022,154,0]}]},"s":{"k":[100,100,100],"ix":6,"a":0},"r":{"k":0,"ix":10,"a":0},"o":{"k":100,"ix":11,"a":0}},"ao":0,"bm":0,"td":1,"refId":"comp_0","w":1842,"h":316},{"nm":"mask_mahi_bottom 2","ddd":0,"ty":0,"ind":2,"sr":1,"ip":0,"op":600,"st":0,"ks":{"a":{"k":[307,119,0],"ix":1,"a":0},"p":{"k":[306,119,0],"ix":2,"a":0},"s":{"k":[100,100,100],"ix":6,"a":0},"r":{"k":0,"ix":10,"a":0},"o":{"k":[{"t":0,"i":{"x":[0.833],"y":[0.833]},"o":{"x":[0.167],"y":[0.167]},"s":[0]},{"t":40,"s":[100]}],"ix":11,"a":1}},"ao":0,"bm":0,"tt":3,"refId":"comp_1","w":614,"h":238},{"nm":"mask_mahi_bottom","ddd":0,"ty":0,"ind":3,"sr":1,"ip":0,"op":600,"st":0,"ks":{"a":{"k":[307,119,0],"ix":1,"a":0},"p":{"k":[306,119,0],"ix":2,"a":0},"s":{"k":[100,100,100],"ix":6,"a":0},"r":{"k":0,"ix":10,"a":0},"o":{"k":[{"t":0,"i":{"x":[0.833],"y":[0.833]},"o":{"x":[0.167],"y":[0.167]},"s":[0]},{"t":40,"s":[100]}],"ix":11,"a":1}},"ao":0,"bm":0,"tt":1,"refId":"comp_2","w":614,"h":238}],"nm":"mahi_box_gradient","v":"5.9.3","fr":60,"ip":0,"op":136,"w":614,"h":238,"ddd":0,"assets":[{"nm":"Pre-comp 1","id":"comp_0","layers":[{"nm":"Shape Layer 5","ddd":0,"ty":4,"ind":1,"parent":3,"sr":1,"ip":0,"op":377,"st":0,"ks":{"a":{"k":[0,0,0],"ix":1,"a":0},"p":{"k":[-1227,0,0],"ix":2,"a":0},"s":{"k":[100,100,100],"ix":6,"a":0},"r":{"k":0,"ix":10,"a":0},"o":{"k":100,"ix":11,"a":0}},"ao":0,"bm":0,"ef":[{"nm":"Gradient Ramp","mn":"ADBE Ramp","ix":1,"ty":5,"ef":[{"nm":"Start of Ramp","mn":"ADBE Ramp-0001","ix":1,"ty":3,"v":{"k":[78,214],"ix":1,"a":0}},{"nm":"Start Color","mn":"ADBE Ramp-0002","ix":2,"ty":2,"v":{"k":[1,1,1,1],"ix":2,"a":0}},{"nm":"End of Ramp","mn":"ADBE Ramp-0003","ix":3,"ty":3,"v":{"k":[576,314],"ix":3,"a":0}},{"nm":"cros.sys.illo.base","mn":"ADBE Ramp-0004","ix":4,"ty":2,"v":{"k":[1,1,1,1],"ix":4,"a":0}},{"nm":"Ramp Shape","mn":"ADBE Ramp-0005","ix":5,"ty":7,"v":{"k":1,"ix":5,"a":0}},{"nm":"Ramp Scatter","mn":"ADBE Ramp-0006","ix":6,"ty":0,"v":{"k":0,"ix":6,"a":0}},{"nm":"Blend With Original","mn":"ADBE Ramp-0007","ix":7,"ty":0,"v":{"k":0,"ix":7,"a":0}},{"nm":"","mn":"ADBE Ramp-0008","ix":8,"ty":6,"v":0}],"en":true}],"shapes":[{"nm":"Rectangle 1","mn":"ADBE Vector Group","hd":false,"ty":"gr","bm":0,"ix":1,"np":3,"it":[{"nm":"Rectangle Path 1","mn":"ADBE Vector Shape - Rect","hd":false,"ty":"rc","d":1,"p":{"k":[0,0],"ix":3,"a":0},"s":{"k":[615.586,170.129],"ix":2,"a":0},"r":{"k":0,"ix":4,"a":0}},{"nm":"cros.sys.illo.base","mn":"ADBE Vector Graphic - Stroke","hd":false,"ty":"st","bm":0,"lc":1,"lj":1,"ml":4,"o":{"k":100,"ix":4,"a":0},"w":{"k":0,"ix":5,"a":0},"c":{"k":[1,1,1,1],"ix":3,"a":0}},{"nm":"cros.sys.base-elevated","mn":"ADBE Vector Graphic - Fill","hd":false,"ty":"fl","bm":0,"o":{"k":100,"ix":5,"a":0},"c":{"k":[1,1,1,1],"ix":4,"a":0},"r":1},{"nm":"Transform","ty":"tr","a":{"k":[0,0],"ix":1,"a":0},"p":{"k":[-1.207,-1.936],"ix":2,"a":0},"s":{"k":[100,100],"ix":3,"a":0},"r":{"k":0,"ix":6,"a":0},"o":{"k":100,"ix":7,"a":0},"sk":{"k":0,"ix":4,"a":0},"sa":{"k":0,"ix":5,"a":0}}]}]},{"nm":"Shape Layer 3","ddd":0,"ty":4,"ind":2,"parent":3,"sr":1,"ip":0,"op":405,"st":0,"ks":{"a":{"k":[0,0,0],"ix":1,"a":0},"p":{"k":[-613,0,0],"ix":2,"a":0},"s":{"k":[100,100,100],"ix":6,"a":0},"r":{"k":0,"ix":10,"a":0},"o":{"k":100,"ix":11,"a":0}},"ao":0,"bm":0,"ef":[{"nm":"Gradient Ramp","mn":"ADBE Ramp","ix":1,"ty":5,"ef":[{"nm":"Start of Ramp","mn":"ADBE Ramp-0001","ix":1,"ty":3,"v":{"k":[1093,227],"ix":1,"a":0}},{"nm":"Start Color","mn":"ADBE Ramp-0002","ix":2,"ty":2,"v":{"k":[1,1,1,1],"ix":2,"a":0}},{"nm":"End of Ramp","mn":"ADBE Ramp-0003","ix":3,"ty":3,"v":{"k":[680,78],"ix":3,"a":0}},{"nm":"cros.sys.illo.base","mn":"ADBE Ramp-0004","ix":4,"ty":2,"v":{"k":[1,1,1,1],"ix":4,"a":0}},{"nm":"Ramp Shape","mn":"ADBE Ramp-0005","ix":5,"ty":7,"v":{"k":1,"ix":5,"a":0}},{"nm":"Ramp Scatter","mn":"ADBE Ramp-0006","ix":6,"ty":0,"v":{"k":0,"ix":6,"a":0}},{"nm":"Blend With Original","mn":"ADBE Ramp-0007","ix":7,"ty":0,"v":{"k":0,"ix":7,"a":0}},{"nm":"","mn":"ADBE Ramp-0008","ix":8,"ty":6,"v":0}],"en":true}],"shapes":[{"nm":"Rectangle 1","mn":"ADBE Vector Group","hd":false,"ty":"gr","bm":0,"ix":1,"np":3,"it":[{"nm":"Rectangle Path 1","mn":"ADBE Vector Shape - Rect","hd":false,"ty":"rc","d":1,"p":{"k":[0,0],"ix":3,"a":0},"s":{"k":[615.586,170.129],"ix":2,"a":0},"r":{"k":0,"ix":4,"a":0}},{"nm":"cros.sys.illo.base","mn":"ADBE Vector Graphic - Stroke","hd":false,"ty":"st","bm":0,"lc":1,"lj":1,"ml":4,"o":{"k":100,"ix":4,"a":0},"w":{"k":0,"ix":5,"a":0},"c":{"k":[1,1,1,1],"ix":3,"a":0}},{"nm":"cros.sys.base-elevated","mn":"ADBE Vector Graphic - Fill","hd":false,"ty":"fl","bm":0,"o":{"k":100,"ix":5,"a":0},"c":{"k":[1,1,1,1],"ix":4,"a":0},"r":1},{"nm":"Transform","ty":"tr","a":{"k":[0,0],"ix":1,"a":0},"p":{"k":[-1.207,-1.936],"ix":2,"a":0},"s":{"k":[100,100],"ix":3,"a":0},"r":{"k":0,"ix":6,"a":0},"o":{"k":100,"ix":7,"a":0},"sk":{"k":0,"ix":4,"a":0},"sa":{"k":0,"ix":5,"a":0}}]}]},{"nm":"Shape Layer 4","ddd":0,"ty":4,"ind":3,"sr":1,"ip":-37,"op":339,"st":33,"ks":{"a":{"k":[0,0,0],"ix":1,"a":0},"p":{"k":[1535.2,172,0],"ix":2,"a":0},"s":{"k":[100,214.943,100],"ix":6,"a":0},"r":{"k":0,"ix":10,"a":0},"o":{"k":100,"ix":11,"a":0}},"ao":0,"bm":0,"ef":[{"nm":"Gradient Ramp","mn":"ADBE Ramp","ix":1,"ty":5,"ef":[{"nm":"Start of Ramp","mn":"ADBE Ramp-0001","ix":1,"ty":3,"v":{"k":[1774,314],"ix":1,"a":0}},{"nm":"cros.sys.illo.base","mn":"ADBE Ramp-0002","ix":2,"ty":2,"v":{"k":[1,1,1,1],"ix":2,"a":0}},{"nm":"End of Ramp","mn":"ADBE Ramp-0003","ix":3,"ty":3,"v":{"k":[1317,216],"ix":3,"a":0}},{"nm":"End Color","mn":"ADBE Ramp-0004","ix":4,"ty":2,"v":{"k":[1,1,1,1],"ix":4,"a":0}},{"nm":"Ramp Shape","mn":"ADBE Ramp-0005","ix":5,"ty":7,"v":{"k":1,"ix":5,"a":0}},{"nm":"Ramp Scatter","mn":"ADBE Ramp-0006","ix":6,"ty":0,"v":{"k":0,"ix":6,"a":0}},{"nm":"Blend With Original","mn":"ADBE Ramp-0007","ix":7,"ty":0,"v":{"k":0,"ix":7,"a":0}},{"nm":"","mn":"ADBE Ramp-0008","ix":8,"ty":6,"v":0}],"en":true}],"shapes":[{"nm":"Rectangle 1","mn":"ADBE Vector Group","hd":false,"ty":"gr","bm":0,"ix":1,"np":3,"it":[{"nm":"Rectangle Path 1","mn":"ADBE Vector Shape - Rect","hd":false,"ty":"rc","d":1,"p":{"k":[0,0],"ix":3,"a":0},"s":{"k":[615.586,170.129],"ix":2,"a":0},"r":{"k":0,"ix":4,"a":0}},{"nm":"cros.sys.illo.base","mn":"ADBE Vector Graphic - Stroke","hd":false,"ty":"st","bm":0,"lc":1,"lj":1,"ml":4,"o":{"k":100,"ix":4,"a":0},"w":{"k":0,"ix":5,"a":0},"c":{"k":[1,1,1,1],"ix":3,"a":0}},{"nm":"cros.sys.base-elevated","mn":"ADBE Vector Graphic - Fill","hd":false,"ty":"fl","bm":0,"o":{"k":100,"ix":5,"a":0},"c":{"k":[1,1,1,1],"ix":4,"a":0},"r":1},{"nm":"Transform","ty":"tr","a":{"k":[0,0],"ix":1,"a":0},"p":{"k":[-1.207,-1.936],"ix":2,"a":0},"s":{"k":[100,100],"ix":3,"a":0},"r":{"k":0,"ix":6,"a":0},"o":{"k":100,"ix":7,"a":0},"sk":{"k":0,"ix":4,"a":0},"sa":{"k":0,"ix":5,"a":0}}]}]}],"fr":60},{"nm":"mask_mahi_bottom 2","id":"comp_1","layers":[{"nm":"Shape Layer 2","ddd":0,"ty":4,"ind":1,"sr":1,"ip":0,"op":1125,"st":0,"ks":{"a":{"k":[0,0,0],"ix":1,"a":0},"p":{"k":[300,116,0],"ix":2,"a":0},"s":{"k":[100,100,100],"ix":6,"a":0},"r":{"k":0,"ix":10,"a":0},"o":{"k":100,"ix":11,"a":0}},"ao":0,"bm":0,"shapes":[{"nm":"Rectangle 1","mn":"ADBE Vector Group","hd":false,"ty":"gr","bm":0,"ix":1,"np":3,"it":[{"nm":"Rectangle Path 1","mn":"ADBE Vector Shape - Rect","hd":false,"ty":"rc","d":1,"p":{"k":[0,0],"ix":3,"a":0},"s":{"k":[606.812,101.531],"ix":2,"a":0},"r":{"k":31,"ix":4,"a":0}},{"nm":"cros.sys.illo.analog","mn":"ADBE Vector Graphic - Stroke","hd":false,"ty":"st","bm":0,"lc":1,"lj":1,"ml":4,"o":{"k":100,"ix":4,"a":0},"w":{"k":0,"ix":5,"a":0},"c":{"k":[0.615686274509804,0.6392156862745098,1,1],"ix":3,"a":0}},{"nm":"cros.sys.illo.complement","mn":"ADBE Vector Graphic - Fill","hd":false,"ty":"fl","bm":0,"o":{"k":100,"ix":5,"a":0},"c":{"k":[0.7019607843137254,0.9372549019607843,0.8313725490196079,1],"ix":4,"a":0},"r":1},{"nm":"Transform","ty":"tr","a":{"k":[0,0],"ix":1,"a":0},"p":{"k":[7.406,62.266],"ix":2,"a":0},"s":{"k":[100,100],"ix":3,"a":0},"r":{"k":0,"ix":6,"a":0},"o":{"k":100,"ix":7,"a":0},"sk":{"k":0,"ix":4,"a":0},"sa":{"k":0,"ix":5,"a":0}}]}]},{"nm":"Shape Layer 1","ddd":0,"ty":4,"ind":2,"sr":1,"ip":0,"op":1125,"st":0,"ks":{"a":{"k":[0,0,0],"ix":1,"a":0},"p":{"k":[300,-4,0],"ix":2,"a":0},"s":{"k":[100,100,100],"ix":6,"a":0},"r":{"k":0,"ix":10,"a":0},"o":{"k":100,"ix":11,"a":0}},"ao":0,"bm":0,"shapes":[{"nm":"Rectangle 1","mn":"ADBE Vector Group","hd":false,"ty":"gr","bm":0,"ix":1,"np":3,"it":[{"nm":"Rectangle Path 1","mn":"ADBE Vector Shape - Rect","hd":false,"ty":"rc","d":1,"p":{"k":[0,0],"ix":3,"a":0},"s":{"k":[606.812,101.531],"ix":2,"a":0},"r":{"k":31,"ix":4,"a":0}},{"nm":"Stroke 1","mn":"ADBE Vector Graphic - Stroke","hd":false,"ty":"st","bm":0,"lc":1,"lj":1,"ml":4,"o":{"k":100,"ix":4,"a":0},"w":{"k":0,"ix":5,"a":0},"c":{"k":[0.556862984452,0.658824008119,0.992156982422,1],"ix":3,"a":0}},{"nm":"cros.sys.illo.complement","mn":"ADBE Vector Graphic - Fill","hd":false,"ty":"fl","bm":0,"o":{"k":100,"ix":5,"a":0},"c":{"k":[0.7019607843137254,0.9372549019607843,0.8313725490196079,1],"ix":4,"a":0},"r":1},{"nm":"Transform","ty":"tr","a":{"k":[0,0],"ix":1,"a":0},"p":{"k":[7.406,62.266],"ix":2,"a":0},"s":{"k":[100,100],"ix":3,"a":0},"r":{"k":0,"ix":6,"a":0},"o":{"k":100,"ix":7,"a":0},"sk":{"k":0,"ix":4,"a":0},"sa":{"k":0,"ix":5,"a":0}}]}]}],"fr":60},{"nm":"mask_mahi_bottom","id":"comp_2","layers":[{"nm":"Shape Layer 2","ddd":0,"ty":4,"ind":1,"sr":1,"ip":0,"op":1125,"st":0,"ks":{"a":{"k":[0,0,0],"ix":1,"a":0},"p":{"k":[300,116,0],"ix":2,"a":0},"s":{"k":[100,100,100],"ix":6,"a":0},"r":{"k":0,"ix":10,"a":0},"o":{"k":100,"ix":11,"a":0}},"ao":0,"bm":0,"shapes":[{"nm":"Rectangle 1","mn":"ADBE Vector Group","hd":false,"ty":"gr","bm":0,"ix":1,"np":3,"it":[{"nm":"Rectangle Path 1","mn":"ADBE Vector Shape - Rect","hd":false,"ty":"rc","d":1,"p":{"k":[0,0],"ix":3,"a":0},"s":{"k":[606.812,101.531],"ix":2,"a":0},"r":{"k":31,"ix":4,"a":0}},{"nm":"cros.sys.illo.analog","mn":"ADBE Vector Graphic - Stroke","hd":false,"ty":"st","bm":0,"lc":1,"lj":1,"ml":4,"o":{"k":100,"ix":4,"a":0},"w":{"k":0,"ix":5,"a":0},"c":{"k":[0.615686274509804,0.6392156862745098,1,1],"ix":3,"a":0}},{"nm":"cros.sys.illo.analog","mn":"ADBE Vector Graphic - Fill","hd":false,"ty":"fl","bm":0,"o":{"k":100,"ix":5,"a":0},"c":{"k":[0.615686274509804,0.6392156862745098,1,1],"ix":4,"a":0},"r":1},{"nm":"Transform","ty":"tr","a":{"k":[0,0],"ix":1,"a":0},"p":{"k":[7.406,62.266],"ix":2,"a":0},"s":{"k":[100,100],"ix":3,"a":0},"r":{"k":0,"ix":6,"a":0},"o":{"k":100,"ix":7,"a":0},"sk":{"k":0,"ix":4,"a":0},"sa":{"k":0,"ix":5,"a":0}}]}]},{"nm":"Shape Layer 1","ddd":0,"ty":4,"ind":2,"sr":1,"ip":0,"op":1125,"st":0,"ks":{"a":{"k":[0,0,0],"ix":1,"a":0},"p":{"k":[300,-4,0],"ix":2,"a":0},"s":{"k":[100,100,100],"ix":6,"a":0},"r":{"k":0,"ix":10,"a":0},"o":{"k":100,"ix":11,"a":0}},"ao":0,"bm":0,"shapes":[{"nm":"Rectangle 1","mn":"ADBE Vector Group","hd":false,"ty":"gr","bm":0,"ix":1,"np":3,"it":[{"nm":"Rectangle Path 1","mn":"ADBE Vector Shape - Rect","hd":false,"ty":"rc","d":1,"p":{"k":[0,0],"ix":3,"a":0},"s":{"k":[606.812,101.531],"ix":2,"a":0},"r":{"k":31,"ix":4,"a":0}},{"nm":"Stroke 1","mn":"ADBE Vector Graphic - Stroke","hd":false,"ty":"st","bm":0,"lc":1,"lj":1,"ml":4,"o":{"k":100,"ix":4,"a":0},"w":{"k":0,"ix":5,"a":0},"c":{"k":[0.556862984452,0.658824008119,0.992156982422,1],"ix":3,"a":0}},{"nm":"cros.sys.illo.analog","mn":"ADBE Vector Graphic - Fill","hd":false,"ty":"fl","bm":0,"o":{"k":100,"ix":5,"a":0},"c":{"k":[0.615686274509804,0.6392156862745098,1,1],"ix":4,"a":0},"r":1},{"nm":"Transform","ty":"tr","a":{"k":[0,0],"ix":1,"a":0},"p":{"k":[7.406,62.266],"ix":2,"a":0},"s":{"k":[100,100],"ix":3,"a":0},"r":{"k":0,"ix":6,"a":0},"o":{"k":100,"ix":7,"a":0},"sk":{"k":0,"ix":4,"a":0},"sa":{"k":0,"ix":5,"a":0}}]}]}],"fr":60}],"markers":[{"cm":"_CrOS_Marker_CycleRestart_Box","tm":40,"dr":0}]}