{
  "$build/chromium_tests_builder_config": {
    "builder_config": {
      "builder_db": {
        "entries": [
          {
            "builder_id": {
              "bucket": "ci",
              "builder": "Android arm64 Builder (dbg)",
              "project": "chromium"
            },
            "builder_spec": {
              "build_gs_bucket": "chromium-android-archive",
              "builder_group": "chromium.android",
              "execution_mode": "COMPILE_AND_TEST",
              "legacy_android_config": {
                "config": "main_builder_mb"
              },
              "legacy_chromium_config": {
                "apply_configs": [
                  "download_xr_test_apks"
                ],
                "build_config": "Debug",
                "config": "android",
                "target_bits": 64,
                "target_platform": "android"
              },
              "legacy_gclient_config": {
                "apply_configs": [
                  "android"
                ],
                "config": "chromium"
              }
            }
          },
          {
            "builder_id": {
              "bucket": "ci",
              "builder": "android-pie-arm64-dbg",
              "project": "chromium"
            },
            "builder_spec": {
              "build_gs_bucket": "chromium-android-archive",
              "builder_group": "chromium.android",
              "execution_mode": "TEST",
              "legacy_android_config": {
                "config": "main_builder_mb"
              },
              "legacy_chromium_config": {
                "apply_configs": [
                  "download_xr_test_apks"
                ],
                "build_config": "Debug",
                "config": "android",
                "target_bits": 64,
                "target_platform": "android"
              },
              "legacy_gclient_config": {
                "apply_configs": [
                  "android"
                ],
                "config": "chromium"
              },
              "parent": {
                "bucket": "ci",
                "builder": "Android arm64 Builder (dbg)",
                "project": "chromium"
              }
            }
          }
        ]
      },
      "builder_ids": [
        {
          "bucket": "ci",
          "builder": "android-pie-arm64-dbg",
          "project": "chromium"
        }
      ],
      "mirroring_builder_group_and_names": [
        {
          "builder": "android-pie-arm64-dbg",
          "group": "tryserver.chromium.android"
        },
        {
          "builder": "android_arm64_dbg_recipe",
          "group": "tryserver.chromium.android"
        }
      ],
      "targets_spec_directory": "src/infra/config/generated/builders/ci/android-pie-arm64-dbg/targets"
    }
  },
  "$recipe_engine/resultdb/test_presentation": {
    "column_keys": [],
    "grouping_keys": [
      "status",
      "v.test_suite"
    ]
  },
  "builder_group": "chromium.android",
  "gardener_rotations": [
    "android"
  ],
  "recipe": "chromium",
  "sheriff_rotations": [
    "android"
  ]
}