{
  "Android WebView O (dbg)": {
    "gtest_tests": [
      {
        "args": [
          "--gs-results-bucket=chromium-result-details",
          "--recover-devices"
        ],
        "merge": {
          "args": [
            "--bucket",
            "chromium-result-details",
            "--test-name",
            "android_webview_unittests"
          ],
          "script": "//build/android/pylib/results/presentation/test_results_presentation.py"
        },
        "name": "android_webview_unittests",
        "resultdb": {
          "enable": true,
          "has_native_resultdb_integration": true
        },
        "swarming": {
          "dimensions": {
            "device_os": "OPM4.171019.021.P2",
            "device_os_flavor": "google",
            "device_os_type": "userdebug",
            "device_type": "walleye",
            "os": "Android"
          },
          "expiration": 10800,
          "service_account": "chromium-tester@chops-service-accounts.iam.gserviceaccount.com"
        },
        "test": "android_webview_unittests",
        "test_id_prefix": "ninja://android_webview/test:android_webview_unittests/"
      },
      {
        "args": [
          "--gs-results-bucket=chromium-result-details",
          "--recover-devices"
        ],
        "merge": {
          "args": [
            "--bucket",
            "chromium-result-details",
            "--test-name",
            "system_webview_shell_layout_test_apk"
          ],
          "script": "//build/android/pylib/results/presentation/test_results_presentation.py"
        },
        "name": "system_webview_shell_layout_test_apk",
        "resultdb": {
          "enable": true,
          "has_native_resultdb_integration": true
        },
        "swarming": {
          "dimensions": {
            "device_os": "OPM4.171019.021.P2",
            "device_os_flavor": "google",
            "device_os_type": "userdebug",
            "device_type": "walleye",
            "os": "Android"
          },
          "expiration": 10800,
          "service_account": "chromium-tester@chops-service-accounts.iam.gserviceaccount.com"
        },
        "test": "system_webview_shell_layout_test_apk",
        "test_id_prefix": "ninja://android_webview/tools/system_webview_shell:system_webview_shell_layout_test_apk/"
      },
      {
        "args": [
          "--store-tombstones",
          "--gs-results-bucket=chromium-result-details",
          "--recover-devices"
        ],
        "merge": {
          "args": [
            "--bucket",
            "chromium-result-details",
            "--test-name",
            "webview_cts_tests"
          ],
          "script": "//build/android/pylib/results/presentation/test_results_presentation.py"
        },
        "name": "webview_cts_tests",
        "resultdb": {
          "enable": true,
          "has_native_resultdb_integration": true
        },
        "swarming": {
          "cipd_packages": [
            {
              "cipd_package": "chromium/android_webview/tools/cts_archive",
              "location": "android_webview/tools/cts_archive/cipd",
              "revision": "UYQZhJpB3MWpJIAcesI-M1bqRoTghiKCYr_SD9tPDewC"
            }
          ],
          "dimensions": {
            "device_os": "OPM4.171019.021.P2",
            "device_os_flavor": "google",
            "device_os_type": "userdebug",
            "device_type": "walleye",
            "os": "Android"
          },
          "expiration": 10800,
          "service_account": "chromium-tester@chops-service-accounts.iam.gserviceaccount.com",
          "shards": 2
        },
        "test": "webview_cts_tests",
        "test_id_prefix": "ninja://android_webview/test:webview_cts_tests/"
      },
      {
        "args": [
          "--disable-field-trial-config",
          "--store-tombstones",
          "--gs-results-bucket=chromium-result-details",
          "--recover-devices"
        ],
        "merge": {
          "args": [
            "--bucket",
            "chromium-result-details",
            "--test-name",
            "webview_cts_tests_no_field_trial"
          ],
          "script": "//build/android/pylib/results/presentation/test_results_presentation.py"
        },
        "name": "webview_cts_tests_no_field_trial",
        "resultdb": {
          "enable": true,
          "has_native_resultdb_integration": true
        },
        "swarming": {
          "cipd_packages": [
            {
              "cipd_package": "chromium/android_webview/tools/cts_archive",
              "location": "android_webview/tools/cts_archive/cipd",
              "revision": "UYQZhJpB3MWpJIAcesI-M1bqRoTghiKCYr_SD9tPDewC"
            }
          ],
          "dimensions": {
            "device_os": "OPM4.171019.021.P2",
            "device_os_flavor": "google",
            "device_os_type": "userdebug",
            "device_type": "walleye",
            "os": "Android"
          },
          "expiration": 10800,
          "service_account": "chromium-tester@chops-service-accounts.iam.gserviceaccount.com",
          "shards": 2
        },
        "test": "webview_cts_tests",
        "test_id_prefix": "ninja://android_webview/test:webview_cts_tests/"
      },
      {
        "args": [
          "--use-apk-under-test-flags-file",
          "--webview-mutations-enabled",
          "--gs-results-bucket=chromium-result-details",
          "--recover-devices"
        ],
        "merge": {
          "args": [
            "--bucket",
            "chromium-result-details",
            "--test-name",
            "webview_instrumentation_test_apk_mutations"
          ],
          "script": "//build/android/pylib/results/presentation/test_results_presentation.py"
        },
        "name": "webview_instrumentation_test_apk_mutations",
        "resultdb": {
          "enable": true,
          "has_native_resultdb_integration": true
        },
        "swarming": {
          "dimensions": {
            "device_os": "OPM4.171019.021.P2",
            "device_os_flavor": "google",
            "device_os_type": "userdebug",
            "device_type": "walleye",
            "os": "Android"
          },
          "expiration": 10800,
          "service_account": "chromium-tester@chops-service-accounts.iam.gserviceaccount.com",
          "shards": 12
        },
        "test": "webview_instrumentation_test_apk",
        "test_id_prefix": "ninja://android_webview/test:webview_instrumentation_test_apk/"
      },
      {
        "args": [
          "--disable-field-trial-config",
          "--use-apk-under-test-flags-file",
          "--gs-results-bucket=chromium-result-details",
          "--recover-devices"
        ],
        "merge": {
          "args": [
            "--bucket",
            "chromium-result-details",
            "--test-name",
            "webview_instrumentation_test_apk_no_field_trial"
          ],
          "script": "//build/android/pylib/results/presentation/test_results_presentation.py"
        },
        "name": "webview_instrumentation_test_apk_no_field_trial",
        "resultdb": {
          "enable": true,
          "has_native_resultdb_integration": true
        },
        "swarming": {
          "dimensions": {
            "device_os": "OPM4.171019.021.P2",
            "device_os_flavor": "google",
            "device_os_type": "userdebug",
            "device_type": "walleye",
            "os": "Android"
          },
          "expiration": 10800,
          "service_account": "chromium-tester@chops-service-accounts.iam.gserviceaccount.com",
          "shards": 12
        },
        "test": "webview_instrumentation_test_apk",
        "test_id_prefix": "ninja://android_webview/test:webview_instrumentation_test_apk/"
      },
      {
        "args": [
          "--gs-results-bucket=chromium-result-details",
          "--recover-devices"
        ],
        "merge": {
          "args": [
            "--bucket",
            "chromium-result-details",
            "--test-name",
            "webview_ui_test_app_test_apk"
          ],
          "script": "//build/android/pylib/results/presentation/test_results_presentation.py"
        },
        "name": "webview_ui_test_app_test_apk",
        "resultdb": {
          "enable": true,
          "has_native_resultdb_integration": true
        },
        "swarming": {
          "dimensions": {
            "device_os": "OPM4.171019.021.P2",
            "device_os_flavor": "google",
            "device_os_type": "userdebug",
            "device_type": "walleye",
            "os": "Android"
          },
          "expiration": 10800,
          "service_account": "chromium-tester@chops-service-accounts.iam.gserviceaccount.com"
        },
        "test": "webview_ui_test_app_test_apk",
        "test_id_prefix": "ninja://android_webview/tools/automated_ui_tests:webview_ui_test_app_test_apk/"
      },
      {
        "args": [
          "--disable-field-trial-config",
          "--gs-results-bucket=chromium-result-details",
          "--recover-devices"
        ],
        "merge": {
          "args": [
            "--bucket",
            "chromium-result-details",
            "--test-name",
            "webview_ui_test_app_test_apk_no_field_trial"
          ],
          "script": "//build/android/pylib/results/presentation/test_results_presentation.py"
        },
        "name": "webview_ui_test_app_test_apk_no_field_trial",
        "resultdb": {
          "enable": true,
          "has_native_resultdb_integration": true
        },
        "swarming": {
          "dimensions": {
            "device_os": "OPM4.171019.021.P2",
            "device_os_flavor": "google",
            "device_os_type": "userdebug",
            "device_type": "walleye",
            "os": "Android"
          },
          "expiration": 10800,
          "service_account": "chromium-tester@chops-service-accounts.iam.gserviceaccount.com"
        },
        "test": "webview_ui_test_app_test_apk",
        "test_id_prefix": "ninja://android_webview/tools/automated_ui_tests:webview_ui_test_app_test_apk/"
      }
    ]
  }
}