{
  "schema": "pedal_concepts_runtime",
  "schema_version": 1,
  "data_version": 15538875,
  "tokenize_characters": " -",
  "dictionary": [
    "chrome",
    "cookie",
    "google",
    "анонимный",
    "банковская",
    "браузер",
    "в",
    "вкладка",
    "внутри",
    "данные",
    "делать",
    "для",
    "запустить",
    "изменить",
    "инкогнито",
    "информацию",
    "информация",
    "исправить",
    "историю",
    "к",
    "как",
    "карта",
    "карте",
    "карты",
    "кеш",
    "кредитной",
    "кредитные",
    "мне",
    "мой",
    "на",
    "нужно",
    "о",
    "обновить",
    "обновление",
    "один",
    "окно",
    "оплаты",
    "открыть",
    "очистить",
    "пароли",
    "пароль",
    "перевести",
    "перейти",
    "платеж",
    "платежи",
    "платежные",
    "показать",
    "посмотреть",
    "почистить",
    "приватная",
    "приватное",
    "приватный",
    "просмотр",
    "режим",
    "реквизиты",
    "сведения",
    "сменить",
    "создать",
    "сохранить",
    "способы",
    "стереть",
    "страницу",
    "тот",
    "убрать",
    "удалить",
    "управление",
    "управлять",
    "установить",
    "учетные",
    "файлы",
    "хочу",
    "это",
    "этот",
    "эту",
    "я",
    "язык"
  ],
  "pedals": [
    {
      "name": "CLEAR_BROWSING_DATA",
      "id": 1,
      "groups": [
        {
          "required": false,
          "single": true,
          "synonyms": [
            [
              2,
              0
            ],
            [
              52
            ],
            [
              5
            ],
            [
              0
            ]
          ]
        },
        {
          "required": true,
          "single": true,
          "synonyms": [
            [
              48
            ],
            [
              38
            ],
            [
              60
            ],
            [
              64
            ],
            [
              63
            ]
          ]
        },
        {
          "required": true,
          "single": true,
          "synonyms": [
            [
              69,
              1
            ],
            [
              15
            ],
            [
              55
            ],
            [
              18
            ],
            [
              9
            ],
            [
              24
            ]
          ]
        }
      ]
    },
    {
      "name": "MANAGE_PASSWORDS",
      "id": 2,
      "groups": [
        {
          "required": false,
          "single": true,
          "synonyms": [
            [
              2,
              0
            ],
            [
              5
            ],
            [
              0
            ]
          ]
        },
        {
          "required": true,
          "single": true,
          "synonyms": [
            [
              47
            ],
            [
              65
            ],
            [
              58
            ],
            [
              66
            ],
            [
              13
            ],
            [
              32
            ],
            [
              46
            ],
            [
              56
            ]
          ]
        },
        {
          "required": true,
          "single": true,
          "synonyms": [
            [
              68,
              9
            ],
            [
              39
            ],
            [
              40
            ]
          ]
        }
      ]
    },
    {
      "name": "UPDATE_CREDIT_CARD",
      "id": 3,
      "groups": [
        {
          "required": false,
          "single": true,
          "synonyms": [
            [
              2,
              0
            ],
            [
              5
            ],
            [
              0
            ]
          ]
        },
        {
          "required": true,
          "single": true,
          "synonyms": [
            [
              65
            ],
            [
              17
            ],
            [
              58
            ],
            [
              13
            ],
            [
              32
            ]
          ]
        },
        {
          "required": true,
          "single": true,
          "synonyms": [
            [
              9,
              25,
              23
            ],
            [
              16,
              31,
              22
            ],
            [
              55,
              31,
              22
            ],
            [
              4,
              21
            ],
            [
              45,
              9
            ],
            [
              26,
              23
            ],
            [
              59,
              36
            ],
            [
              9,
              23
            ],
            [
              54
            ],
            [
              44
            ],
            [
              43
            ],
            [
              23
            ]
          ]
        }
      ]
    },
    {
      "name": "LAUNCH_INCOGNITO",
      "id": 4,
      "groups": [
        {
          "required": false,
          "single": true,
          "synonyms": [
            [
              2,
              0
            ],
            [
              5
            ],
            [
              0
            ]
          ]
        },
        {
          "required": false,
          "single": true,
          "synonyms": [
            [
              42
            ],
            [
              42
            ],
            [
              12
            ],
            [
              37
            ],
            [
              57
            ]
          ]
        },
        {
          "required": true,
          "single": true,
          "synonyms": [
            [
              3,
              52
            ],
            [
              7,
              14
            ],
            [
              49,
              7
            ],
            [
              3,
              53
            ],
            [
              51,
              53
            ],
            [
              53,
              14
            ],
            [
              35,
              14
            ],
            [
              50,
              35
            ],
            [
              14
            ]
          ]
        }
      ]
    },
    {
      "name": "TRANSLATE",
      "id": 5,
      "groups": [
        {
          "required": false,
          "single": true,
          "synonyms": [
            [
              2,
              0
            ],
            [
              5
            ],
            [
              0
            ]
          ]
        },
        {
          "required": true,
          "single": true,
          "synonyms": [
            [
              13,
              75
            ],
            [
              41
            ]
          ]
        },
        {
          "required": true,
          "single": true,
          "synonyms": [
            [
              73,
              61
            ],
            [
              61
            ],
            [
              71
            ]
          ]
        }
      ]
    },
    {
      "name": "UPDATE_CHROME",
      "id": 6,
      "groups": [
        {
          "required": true,
          "single": true,
          "synonyms": [
            [
              2,
              0
            ],
            [
              5
            ],
            [
              0
            ]
          ]
        },
        {
          "required": true,
          "single": true,
          "synonyms": [
            [
              67,
              33
            ],
            [
              67
            ],
            [
              32
            ]
          ]
        }
      ]
    }
  ],
  "ignore_group": {
    "required": false,
    "single": false,
    "synonyms": [
      [
        8
      ],
      [
        10
      ],
      [
        30
      ],
      [
        72
      ],
      [
        34
      ],
      [
        70
      ],
      [
        11
      ],
      [
        20
      ],
      [
        62
      ],
      [
        28
      ],
      [
        27
      ],
      [
        29
      ],
      [
        6
      ],
      [
        6
      ],
      [
        19
      ],
      [
        74
      ]
    ]
  },
  "max_tokens": 32
}