{
  "schema": "pedal_concepts_runtime",
  "schema_version": 1,
  "data_version": 15538875,
  "tokenize_characters": " -",
  "dictionary": [
    "a",
    "an",
    "chrome",
    "ciasteczka",
    "ciastka",
    "cookie",
    "cookies",
    "cookiesy",
    "dane",
    "dla",
    "do",
    "edytuj",
    "formy",
    "formę",
    "google",
    "hasła",
    "hasło",
    "historię",
    "i",
    "in",
    "incognito",
    "info",
    "informacje",
    "ja",
    "jak",
    "język",
    "karcie",
    "karty",
    "kartę",
    "kredytowe",
    "kredytowej",
    "kredytową",
    "login",
    "logowania",
    "menedżer",
    "metody",
    "metodę",
    "mój",
    "na",
    "niewidoczny",
    "niewidzialny",
    "o",
    "okno",
    "otwórz",
    "pamięć",
    "pliki",
    "podręczną",
    "pokaż",
    "prywatne",
    "prywatny",
    "prywatną",
    "przeglądania",
    "przeglądanie",
    "przeglądarce",
    "przeglądarka",
    "przeglądarki",
    "przeglądarkę",
    "przetłumacz",
    "płatnicze",
    "płatniczej",
    "płatniczą",
    "płatności",
    "płatność",
    "się",
    "skasuj",
    "sposób",
    "strony",
    "stronę",
    "szczegóły",
    "słowa",
    "te",
    "tego",
    "tej",
    "tekst",
    "ten",
    "the",
    "to",
    "treść",
    "tryb",
    "tę",
    "tłumacz",
    "uaktualnij",
    "uruchom",
    "usuń",
    "utwórz",
    "w",
    "wewnątrz",
    "wyczyść",
    "wykasuj",
    "wymaż",
    "wyświetl",
    "włącz",
    "z",
    "zainstaluj",
    "zaktualizuj",
    "zalogowania",
    "zalogować",
    "zapisz",
    "zarządzaj",
    "zdanie",
    "zmień",
    "z karty"
  ],
  "pedals": [
    {
      "name": "CLEAR_BROWSING_DATA",
      "id": 1,
      "groups": [
        {
          "required": false,
          "single": true,
          "synonyms": [
            [
              14,
              2
            ],
            [
              52
            ],
            [
              54
            ],
            [
              2
            ]
          ]
        },
        {
          "required": true,
          "single": true,
          "synonyms": [
            [
              87
            ],
            [
              88
            ],
            [
              64
            ],
            [
              89
            ],
            [
              83
            ]
          ]
        },
        {
          "required": true,
          "single": true,
          "synonyms": [
            [
              44,
              46,
              55
            ],
            [
              8,
              92,
              51
            ],
            [
              17,
              53
            ],
            [
              17,
              51
            ],
            [
              17,
              55
            ],
            [
              44,
              51
            ],
            [
              44,
              55
            ],
            [
              44,
              46
            ],
            [
              8,
              51
            ],
            [
              45,
              5
            ],
            [
              3
            ],
            [
              22
            ],
            [
              17
            ],
            [
              7
            ],
            [
              4
            ],
            [
              6
            ],
            [
              5
            ],
            [
              8
            ],
            [
              21
            ]
          ]
        }
      ]
    },
    {
      "name": "MANAGE_PASSWORDS",
      "id": 2,
      "groups": [
        {
          "required": false,
          "single": true,
          "synonyms": [
            [
              14,
              2
            ],
            [
              54
            ],
            [
              2
            ]
          ]
        },
        {
          "required": true,
          "single": true,
          "synonyms": [
            [
              94
            ],
            [
              98
            ],
            [
              34
            ],
            [
              90
            ],
            [
              11
            ],
            [
              47
            ],
            [
              97
            ],
            [
              100
            ]
          ]
        },
        {
          "required": true,
          "single": true,
          "synonyms": [
            [
              32,
              18,
              16
            ],
            [
              8,
              95
            ],
            [
              63,
              96
            ],
            [
              8,
              33
            ],
            [
              65,
              33
            ],
            [
              8,
              33
            ],
            [
              15
            ],
            [
              16
            ],
            [
              32
            ]
          ]
        }
      ]
    },
    {
      "name": "UPDATE_CREDIT_CARD",
      "id": 3,
      "groups": [
        {
          "required": false,
          "single": true,
          "synonyms": [
            [
              14,
              2
            ],
            [
              54
            ],
            [
              2
            ]
          ]
        },
        {
          "required": true,
          "single": true,
          "synonyms": [
            [
              94
            ],
            [
              98
            ],
            [
              11
            ],
            [
              97
            ],
            [
              100
            ]
          ]
        },
        {
          "required": true,
          "single": true,
          "synonyms": [
            [
              22,
              41,
              26,
              59
            ],
            [
              22,
              92,
              27,
              59
            ],
            [
              8,
              92,
              27,
              59
            ],
            [
              8,
              92,
              27,
              30
            ],
            [
              22,
              101,
              30
            ],
            [
              8,
              27,
              59
            ],
            [
              8,
              27,
              30
            ],
            [
              22,
              41,
              26
            ],
            [
              8,
              92,
              27
            ],
            [
              8,
              61
            ],
            [
              22,
              101
            ],
            [
              36,
              61
            ],
            [
              65,
              61
            ],
            [
              13,
              61
            ],
            [
              28,
              60
            ],
            [
              35,
              61
            ],
            [
              12,
              61
            ],
            [
              28,
              31
            ],
            [
              68,
              27
            ],
            [
              8,
              58
            ],
            [
              27,
              29
            ],
            [
              8,
              27
            ],
            [
              61
            ],
            [
              62
            ],
            [
              27
            ]
          ]
        }
      ]
    },
    {
      "name": "LAUNCH_INCOGNITO",
      "id": 4,
      "groups": [
        {
          "required": false,
          "single": true,
          "synonyms": [
            [
              14,
              2
            ],
            [
              54
            ],
            [
              2
            ]
          ]
        },
        {
          "required": false,
          "single": true,
          "synonyms": [
            [
              90
            ],
            [
              43
            ],
            [
              82
            ],
            [
              84
            ],
            [
              91
            ]
          ]
        },
        {
          "required": true,
          "single": true,
          "synonyms": [
            [
              78,
              40
            ],
            [
              28,
              20
            ],
            [
              28,
              50
            ],
            [
              78,
              39
            ],
            [
              42,
              20
            ],
            [
              78,
              20
            ],
            [
              42,
              48
            ],
            [
              78,
              49
            ],
            [
              20
            ]
          ]
        }
      ]
    },
    {
      "name": "TRANSLATE",
      "id": 5,
      "groups": [
        {
          "required": false,
          "single": true,
          "synonyms": [
            [
              14,
              2
            ],
            [
              54
            ],
            [
              2
            ]
          ]
        },
        {
          "required": true,
          "single": true,
          "synonyms": [
            [
              100,
              25
            ],
            [
              57
            ],
            [
              80
            ]
          ]
        },
        {
          "required": true,
          "single": true,
          "synonyms": [
            [
              79,
              67
            ],
            [
              79,
              77
            ],
            [
              72,
              66
            ],
            [
              70,
              69
            ],
            [
              74,
              73
            ],
            [
              76,
              99
            ],
            [
              67
            ],
            [
              66
            ],
            [
              71
            ],
            [
              76
            ]
          ]
        }
      ]
    },
    {
      "name": "UPDATE_CHROME",
      "id": 6,
      "groups": [
        {
          "required": true,
          "single": true,
          "synonyms": [
            [
              14,
              2
            ],
            [
              54
            ],
            [
              2
            ]
          ]
        },
        {
          "required": true,
          "single": true,
          "synonyms": [
            [
              94
            ],
            [
              81
            ],
            [
              93
            ]
          ]
        },
        {
          "required": false,
          "single": true,
          "synonyms": [
            [
              56,
              2
            ],
            [
              56
            ],
            [
              2
            ]
          ]
        }
      ]
    }
  ],
  "ignore_group": {
    "required": false,
    "single": false,
    "synonyms": [
      [
        86
      ],
      [
        37
      ],
      [
        9
      ],
      [
        24
      ],
      [
        75
      ],
      [
        1
      ],
      [
        10
      ],
      [
        19
      ],
      [
        38
      ],
      [
        10
      ],
      [
        23
      ],
      [
        85
      ],
      [
        0
      ]
    ]
  },
  "max_tokens": 32
}